{
  "current_data_version": {
    "zip_sha256": null,
    "raw_file_count": 2327,
    "train_well_count": 773,
    "test_well_count": 3,
    "sample_submission_rows": 14151,
    "created_at": "2026-06-22T06:53:04.723568+00:00"
  },
  "baseline_reference": {
    "rows": null,
    "wells": null,
    "path": "/Users/HIN/ROGII/outputs/baseline_predictions_train_hidden.csv",
    "coverage_threshold": 0.95
  },
  "selected_candidate": null,
  "selected_candidate_eligible_for_auto_submission": false,
  "no_selection_reason": "No coverage-sufficient OOF-evaluated candidates were found.",
  "selection_rule": {
    "primary": "lowest full-coverage OOF RMSE among candidates passing coverage and version checks",
    "coverage_threshold_rows": 0.95,
    "coverage_threshold_wells": 0.95,
    "tie_breakers": [
      "lowest worst_well_rmse",
      "fewest degraded_wells",
      "lowest p95_abs_error"
    ],
    "tie_rmse_tolerance": 0.01,
    "common_coverage_used_for_selection": false,
    "oracle_candidates_excluded_from_auto_selection": true
  },
  "common_comparison": {
    "enabled": false,
    "usable_for_selection": false,
    "used_for_selection": false,
    "reason": "fewer than two full-coverage candidates",
    "common_rows": null,
    "common_wells": null,
    "coverage_vs_baseline_rows": null,
    "coverage_vs_baseline_wells": null
  },
  "available_candidates": [],
  "skipped_candidates": [
    {
      "name": "baseline",
      "kind": "baseline",
      "status": "skipped",
      "reason": "missing OOF: outputs/baseline_predictions_train_hidden.csv",
      "rmse": null,
      "mae": null,
      "p95_abs_error": null,
      "worst_well_rmse": null,
      "degraded_wells": null,
      "improved_wells": null,
      "rows": null,
      "wells": null,
      "baseline_rows": null,
      "baseline_wells": null,
      "coverage_vs_baseline_rows": null,
      "coverage_vs_baseline_wells": null,
      "common_rmse": null,
      "common_mae": null,
      "common_p95_abs_error": null,
      "common_worst_well_rmse": null,
      "common_rows": null,
      "common_wells": null,
      "eligible": false,
      "version_status": "unknown",
      "version_reason": "artifact has version metadata but current data hash is unavailable or unverifiable",
      "artifact_data_hash": "46fd84d5e7e1",
      "run_id": null,
      "metadata_path": "reports/baseline_submission_report.md",
      "duplicate_ids_dropped": 0,
      "oof_path": "/Users/HIN/ROGII/outputs/baseline_predictions_train_hidden.csv",
      "submission_path": "/Users/HIN/ROGII/outputs/baseline_predictions_test.csv",
      "is_postprocessed": false,
      "candidate_type": "validated_candidate",
      "eligible_for_auto_submission": true,
      "candidate_policy_reason": "default candidate policy"
    },
    {
      "name": "geometry",
      "kind": "residual",
      "status": "skipped",
      "reason": "missing OOF: outputs/residual_geometry_oof.csv",
      "rmse": null,
      "mae": null,
      "p95_abs_error": null,
      "worst_well_rmse": null,
      "degraded_wells": null,
      "improved_wells": null,
      "rows": null,
      "wells": null,
      "baseline_rows": null,
      "baseline_wells": null,
      "coverage_vs_baseline_rows": null,
      "coverage_vs_baseline_wells": null,
      "common_rmse": null,
      "common_mae": null,
      "common_p95_abs_error": null,
      "common_worst_well_rmse": null,
      "common_rows": null,
      "common_wells": null,
      "eligible": false,
      "version_status": "unknown",
      "version_reason": "no artifact version metadata found",
      "artifact_data_hash": null,
      "run_id": null,
      "metadata_path": "",
      "duplicate_ids_dropped": 0,
      "oof_path": "/Users/HIN/ROGII/outputs/residual_geometry_oof.csv",
      "submission_path": "/Users/HIN/ROGII/submissions/geometry_residual_submission.csv",
      "is_postprocessed": false,
      "candidate_type": "validated_candidate",
      "eligible_for_auto_submission": true,
      "candidate_policy_reason": "default candidate policy"
    },
    {
      "name": "xgb",
      "kind": "tree_residual",
      "status": "skipped",
      "reason": "missing OOF: outputs/residual_xgb_oof.csv",
      "rmse": null,
      "mae": null,
      "p95_abs_error": null,
      "worst_well_rmse": null,
      "degraded_wells": null,
      "improved_wells": null,
      "rows": null,
      "wells": null,
      "baseline_rows": null,
      "baseline_wells": null,
      "coverage_vs_baseline_rows": null,
      "coverage_vs_baseline_wells": null,
      "common_rmse": null,
      "common_mae": null,
      "common_p95_abs_error": null,
      "common_worst_well_rmse": null,
      "common_rows": null,
      "common_wells": null,
      "eligible": false,
      "version_status": "unknown",
      "version_reason": "no artifact version metadata found",
      "artifact_data_hash": null,
      "run_id": null,
      "metadata_path": "",
      "duplicate_ids_dropped": 0,
      "oof_path": "/Users/HIN/ROGII/outputs/residual_xgb_oof.csv",
      "submission_path": "/Users/HIN/ROGII/submissions/xgb_residual_submission.csv",
      "is_postprocessed": false,
      "candidate_type": "validated_candidate",
      "eligible_for_auto_submission": true,
      "candidate_policy_reason": "default candidate policy"
    },
    {
      "name": "gated_geometry",
      "kind": "gated_residual",
      "status": "skipped",
      "reason": "missing OOF: outputs/gated_geometry_oof.csv",
      "rmse": null,
      "mae": null,
      "p95_abs_error": null,
      "worst_well_rmse": null,
      "degraded_wells": null,
      "improved_wells": null,
      "rows": null,
      "wells": null,
      "baseline_rows": null,
      "baseline_wells": null,
      "coverage_vs_baseline_rows": null,
      "coverage_vs_baseline_wells": null,
      "common_rmse": null,
      "common_mae": null,
      "common_p95_abs_error": null,
      "common_worst_well_rmse": null,
      "common_rows": null,
      "common_wells": null,
      "eligible": false,
      "version_status": "unknown",
      "version_reason": "no artifact version metadata found",
      "artifact_data_hash": null,
      "run_id": null,
      "metadata_path": "",
      "duplicate_ids_dropped": 0,
      "oof_path": "/Users/HIN/ROGII/outputs/gated_geometry_oof.csv",
      "submission_path": "/Users/HIN/ROGII/submissions/gated_geometry_submission.csv",
      "is_postprocessed": false,
      "candidate_type": "oracle_gated_residual",
      "eligible_for_auto_submission": false,
      "candidate_policy_reason": "oracle/diagnostic policy from models/gated_geometry_config.json"
    },
    {
      "name": "learned_gated_geometry",
      "kind": "learned_gated_residual",
      "status": "skipped",
      "reason": "missing OOF: outputs/learned_gated_geometry_oof.csv",
      "rmse": null,
      "mae": null,
      "p95_abs_error": null,
      "worst_well_rmse": null,
      "degraded_wells": null,
      "improved_wells": null,
      "rows": null,
      "wells": null,
      "baseline_rows": null,
      "baseline_wells": null,
      "coverage_vs_baseline_rows": null,
      "coverage_vs_baseline_wells": null,
      "common_rmse": null,
      "common_mae": null,
      "common_p95_abs_error": null,
      "common_worst_well_rmse": null,
      "common_rows": null,
      "common_wells": null,
      "eligible": false,
      "version_status": "unknown",
      "version_reason": "no artifact version metadata found",
      "artifact_data_hash": null,
      "run_id": null,
      "metadata_path": "",
      "duplicate_ids_dropped": 0,
      "oof_path": "/Users/HIN/ROGII/outputs/learned_gated_geometry_oof.csv",
      "submission_path": "/Users/HIN/ROGII/submissions/learned_gated_geometry_submission.csv",
      "is_postprocessed": false,
      "candidate_type": "learned_gated_residual",
      "eligible_for_auto_submission": true,
      "candidate_policy_reason": "default candidate policy"
    },
    {
      "name": "xgb_leftover",
      "kind": "stacked_tree_residual",
      "status": "skipped",
      "reason": "missing OOF: outputs/residual_xgb_leftover_oof.csv",
      "rmse": null,
      "mae": null,
      "p95_abs_error": null,
      "worst_well_rmse": null,
      "degraded_wells": null,
      "improved_wells": null,
      "rows": null,
      "wells": null,
      "baseline_rows": null,
      "baseline_wells": null,
      "coverage_vs_baseline_rows": null,
      "coverage_vs_baseline_wells": null,
      "common_rmse": null,
      "common_mae": null,
      "common_p95_abs_error": null,
      "common_worst_well_rmse": null,
      "common_rows": null,
      "common_wells": null,
      "eligible": false,
      "version_status": "unknown",
      "version_reason": "no artifact version metadata found",
      "artifact_data_hash": null,
      "run_id": null,
      "metadata_path": "",
      "duplicate_ids_dropped": 0,
      "oof_path": "/Users/HIN/ROGII/outputs/residual_xgb_leftover_oof.csv",
      "submission_path": "/Users/HIN/ROGII/submissions/xgb_leftover_submission.csv",
      "is_postprocessed": false,
      "candidate_type": "validated_candidate",
      "eligible_for_auto_submission": true,
      "candidate_policy_reason": "default candidate policy"
    },
    {
      "name": "gated_geometry_plus_xgb_leftover",
      "kind": "gated_stack",
      "status": "skipped",
      "reason": "missing OOF: outputs/gated_geometry_plus_xgb_leftover_oof.csv",
      "rmse": null,
      "mae": null,
      "p95_abs_error": null,
      "worst_well_rmse": null,
      "degraded_wells": null,
      "improved_wells": null,
      "rows": null,
      "wells": null,
      "baseline_rows": null,
      "baseline_wells": null,
      "coverage_vs_baseline_rows": null,
      "coverage_vs_baseline_wells": null,
      "common_rmse": null,
      "common_mae": null,
      "common_p95_abs_error": null,
      "common_worst_well_rmse": null,
      "common_rows": null,
      "common_wells": null,
      "eligible": false,
      "version_status": "unknown",
      "version_reason": "no artifact version metadata found",
      "artifact_data_hash": null,
      "run_id": null,
      "metadata_path": "",
      "duplicate_ids_dropped": 0,
      "oof_path": "/Users/HIN/ROGII/outputs/gated_geometry_plus_xgb_leftover_oof.csv",
      "submission_path": "/Users/HIN/ROGII/submissions/gated_geometry_plus_xgb_leftover_submission.csv",
      "is_postprocessed": false,
      "candidate_type": "oracle_gated_stack",
      "eligible_for_auto_submission": false,
      "candidate_policy_reason": "oracle/diagnostic policy from models/gated_geometry_plus_xgb_leftover_config.json"
    },
    {
      "name": "conservative",
      "kind": "blend",
      "status": "skipped",
      "reason": "missing OOF: outputs/blend_oof.csv",
      "rmse": null,
      "mae": null,
      "p95_abs_error": null,
      "worst_well_rmse": null,
      "degraded_wells": null,
      "improved_wells": null,
      "rows": null,
      "wells": null,
      "baseline_rows": null,
      "baseline_wells": null,
      "coverage_vs_baseline_rows": null,
      "coverage_vs_baseline_wells": null,
      "common_rmse": null,
      "common_mae": null,
      "common_p95_abs_error": null,
      "common_worst_well_rmse": null,
      "common_rows": null,
      "common_wells": null,
      "eligible": false,
      "version_status": "unknown",
      "version_reason": "no artifact version metadata found",
      "artifact_data_hash": null,
      "run_id": null,
      "metadata_path": "",
      "duplicate_ids_dropped": 0,
      "oof_path": "/Users/HIN/ROGII/outputs/blend_oof.csv",
      "submission_path": "/Users/HIN/ROGII/submissions/conservative_submission.csv",
      "is_postprocessed": false,
      "candidate_type": "validated_candidate",
      "eligible_for_auto_submission": true,
      "candidate_policy_reason": "default candidate policy"
    },
    {
      "name": "balanced",
      "kind": "blend",
      "status": "skipped",
      "reason": "missing OOF: outputs/blend_oof.csv",
      "rmse": null,
      "mae": null,
      "p95_abs_error": null,
      "worst_well_rmse": null,
      "degraded_wells": null,
      "improved_wells": null,
      "rows": null,
      "wells": null,
      "baseline_rows": null,
      "baseline_wells": null,
      "coverage_vs_baseline_rows": null,
      "coverage_vs_baseline_wells": null,
      "common_rmse": null,
      "common_mae": null,
      "common_p95_abs_error": null,
      "common_worst_well_rmse": null,
      "common_rows": null,
      "common_wells": null,
      "eligible": false,
      "version_status": "unknown",
      "version_reason": "no artifact version metadata found",
      "artifact_data_hash": null,
      "run_id": null,
      "metadata_path": "",
      "duplicate_ids_dropped": 0,
      "oof_path": "/Users/HIN/ROGII/outputs/blend_oof.csv",
      "submission_path": "/Users/HIN/ROGII/submissions/balanced_submission.csv",
      "is_postprocessed": false,
      "candidate_type": "validated_candidate",
      "eligible_for_auto_submission": true,
      "candidate_policy_reason": "default candidate policy"
    },
    {
      "name": "aggressive",
      "kind": "blend",
      "status": "skipped",
      "reason": "missing OOF: outputs/blend_oof.csv",
      "rmse": null,
      "mae": null,
      "p95_abs_error": null,
      "worst_well_rmse": null,
      "degraded_wells": null,
      "improved_wells": null,
      "rows": null,
      "wells": null,
      "baseline_rows": null,
      "baseline_wells": null,
      "coverage_vs_baseline_rows": null,
      "coverage_vs_baseline_wells": null,
      "common_rmse": null,
      "common_mae": null,
      "common_p95_abs_error": null,
      "common_worst_well_rmse": null,
      "common_rows": null,
      "common_wells": null,
      "eligible": false,
      "version_status": "unknown",
      "version_reason": "no artifact version metadata found",
      "artifact_data_hash": null,
      "run_id": null,
      "metadata_path": "",
      "duplicate_ids_dropped": 0,
      "oof_path": "/Users/HIN/ROGII/outputs/blend_oof.csv",
      "submission_path": "/Users/HIN/ROGII/submissions/aggressive_submission.csv",
      "is_postprocessed": false,
      "candidate_type": "validated_candidate",
      "eligible_for_auto_submission": true,
      "candidate_policy_reason": "default candidate policy"
    },
    {
      "name": "optimized",
      "kind": "blend",
      "status": "skipped",
      "reason": "missing OOF: outputs/blend_oof.csv",
      "rmse": null,
      "mae": null,
      "p95_abs_error": null,
      "worst_well_rmse": null,
      "degraded_wells": null,
      "improved_wells": null,
      "rows": null,
      "wells": null,
      "baseline_rows": null,
      "baseline_wells": null,
      "coverage_vs_baseline_rows": null,
      "coverage_vs_baseline_wells": null,
      "common_rmse": null,
      "common_mae": null,
      "common_p95_abs_error": null,
      "common_worst_well_rmse": null,
      "common_rows": null,
      "common_wells": null,
      "eligible": false,
      "version_status": "unknown",
      "version_reason": "no artifact version metadata found",
      "artifact_data_hash": null,
      "run_id": null,
      "metadata_path": "",
      "duplicate_ids_dropped": 0,
      "oof_path": "/Users/HIN/ROGII/outputs/blend_oof.csv",
      "submission_path": "/Users/HIN/ROGII/submissions/optimized_submission.csv",
      "is_postprocessed": false,
      "candidate_type": "validated_candidate",
      "eligible_for_auto_submission": true,
      "candidate_policy_reason": "default candidate policy"
    },
    {
      "name": "postprocessed",
      "kind": "postprocess",
      "status": "skipped",
      "reason": "postprocess guard decision=unknown reason=missing postprocess report",
      "rmse": null,
      "mae": null,
      "p95_abs_error": null,
      "worst_well_rmse": null,
      "degraded_wells": null,
      "improved_wells": null,
      "rows": null,
      "wells": null,
      "baseline_rows": null,
      "baseline_wells": null,
      "coverage_vs_baseline_rows": null,
      "coverage_vs_baseline_wells": null,
      "common_rmse": null,
      "common_mae": null,
      "common_p95_abs_error": null,
      "common_worst_well_rmse": null,
      "common_rows": null,
      "common_wells": null,
      "eligible": false,
      "version_status": "unknown",
      "version_reason": "",
      "artifact_data_hash": null,
      "run_id": null,
      "metadata_path": "",
      "duplicate_ids_dropped": 0,
      "oof_path": "/Users/HIN/ROGII/outputs/postprocess_oof_summary.csv",
      "submission_path": "",
      "is_postprocessed": true,
      "candidate_type": "postprocessed_candidate",
      "eligible_for_auto_submission": true,
      "candidate_policy_reason": ""
    }
  ],
  "evaluated_candidates": []
}
